{"appleSKU":"","appleTeamID":"","enableCodelessAutoInitialization":true,"enableUnityGamingServicesAutoInitialization":true,"products":[{"id":"no_ads","type":1,"storeIDs":[],"defaultDescription":{"googleLocale":17,"title":"No ads","description":"Remueve todos los anuncios del juego, podr\\u00e1s seguir duplicando las monedas ganadas al acabar la partida sin tener que ver anuncios."},"screenshotPath":"","applePriceTier":2,"googlePrice":{"data":[0,0,0,0],"num":0.0},"pricingTemplateID":"4638611096702818965","descriptions":[{"googleLocale":4,"title":"No ads","description":"Removes all ads from the game, you'll still be able to double your coins at the end of each game without watching ads."}],"udpPrice":{"data":[0,0,0,0],"num":0.0},"payouts":[]},{"id":"skin_pack","type":1,"storeIDs":[],"defaultDescription":{"googleLocale":17,"title":"Paquete de aspectos","description":"Desbloquea permanentemente las apariencias de Cakawai, Crapsycal, Cacavaquera, Cacalien, Cacanauta, Cacaruto y 20s para Cacaleta en el juego."},"screenshotPath":"","applePriceTier":0,"googlePrice":{"data":[0,0,0,0],"num":0.0},"pricingTemplateID":"4634380198015132040","descriptions":[{"googleLocale":4,"title":"Skin pack","description":"Permanently unlocks the CrapyWaii, Crapsycal, Poowboy, Pooutsider, Crapstronaut, Crapnobi and 20s in-game skins."}],"udpPrice":{"data":[0,0,0,0],"num":0.0},"payouts":[]},{"id":"buy_midas","type":1,"storeIDs":[],"defaultDescription":{"googleLocale":17,"title":"Midas","description":"Desbloquea permanentemente la skin de Midas para Cacaleta en el juego."},"screenshotPath":"","applePriceTier":0,"googlePrice":{"data":[0,0,0,0],"num":0.0},"pricingTemplateID":"4637245490478650692","descriptions":[{"googleLocale":4,"title":"Midas","description":"Permanently unlocks the Midas in-game skin."}],"udpPrice":{"data":[0,0,0,0],"num":0.0},"payouts":[]}]}